odoo/addons/web_action_conditionable/README.rst
odoo/addons/web_action_conditionable/__init__.py
odoo/addons/web_action_conditionable/__manifest__.py
odoo/addons/web_action_conditionable/i18n/es.po
odoo/addons/web_action_conditionable/i18n/hr.po
odoo/addons/web_action_conditionable/i18n/web_action_conditionable.pot
odoo/addons/web_action_conditionable/i18n/zh_CN.po
odoo/addons/web_action_conditionable/readme/CONTRIBUTORS.rst
odoo/addons/web_action_conditionable/readme/DESCRIPTION.rst
odoo/addons/web_action_conditionable/readme/USAGE.rst
odoo/addons/web_action_conditionable/static/description/icon.png
odoo/addons/web_action_conditionable/static/description/index.html
odoo/addons/web_action_conditionable/static/src/js/field_one2many.js
odoo/addons/web_action_conditionable/views/view.xml
odoo12_addon_web_action_conditionable-12.0.1.0.1.dist-info/METADATA
odoo12_addon_web_action_conditionable-12.0.1.0.1.dist-info/WHEEL
odoo12_addon_web_action_conditionable-12.0.1.0.1.dist-info/top_level.txt
odoo12_addon_web_action_conditionable-12.0.1.0.1.dist-info/RECORD
